plot_antenna/Version.py
plot_antenna/__init__.py
plot_antenna/contrib.py
plot_antenna/eznec.py
plot_antenna/plot_antenna.py
plot_antenna-2.3.dist-info/licenses/LICENSE
plot_antenna-2.3.dist-info/METADATA
plot_antenna-2.3.dist-info/WHEEL
plot_antenna-2.3.dist-info/entry_points.txt
plot_antenna-2.3.dist-info/top_level.txt
plot_antenna-2.3.dist-info/RECORD
