Metadata-Version: 2.4
Name: plot-antenna
Version: 2.3
Summary: Antenna plotting program for plotting antenna simulation results
Home-page: https://github.com/schlatterbeck/plot-antenna
Author: Ralf Schlatterbeck
Author-email: Ralf Schlatterbeck <rsc@runtux.com>
License-Expression: MIT
Project-URL: Homepage, https://github.com/schlatterbeck/plot-antenna
Project-URL: Bug Tracker, https://github.com/schlatterbeck/plot-antenna/issues
Platform: Any
Classifier: Development Status :: 5 - Production/Stable
Classifier: Operating System :: OS Independent
Classifier: Programming Language :: Python
Classifier: Intended Audience :: Science/Research
Classifier: Intended Audience :: Other Audience
Requires-Python: >=3.7
License-File: LICENSE
Requires-Dist: matplotlib
Requires-Dist: numpy
Requires-Dist: pandas
Requires-Dist: plotly
Provides-Extra: test
Requires-Dist: pytest; extra == "test"
Requires-Dist: kaleido; extra == "test"
Dynamic: author
Dynamic: home-page
Dynamic: license-file
Dynamic: platform
Dynamic: requires-python
